pygyre/__init__.py
pygyre/_version.py
pygyre-1.4.dist-info/METADATA
pygyre-1.4.dist-info/WHEEL
pygyre-1.4.dist-info/licenses/COPYING
pygyre-1.4.dist-info/licenses/LICENSE
pygyre-1.4.dist-info/RECORD
