Metadata-Version: 2.3
Name: pygyre
Version: 1.4
Summary: Python support for the GYRE stellar oscillation code
Project-URL: Documentation, https://pygyre.readthedocs.org
Project-URL: Repository, https://github.com/rhdtownsend/pygyre/
Project-URL: Issues, https://github.com/rhdtownsend/pygyre/issues
Author-email: Rich Townsend <rhtownsend@wisc.edu>
License-File: COPYING
License-File: LICENSE
Classifier: License :: OSI Approved :: GNU General Public License v3 (GPLv3)
Classifier: Operating System :: OS Independent
Classifier: Programming Language :: Python :: 3
Requires-Python: >=3.7
Requires-Dist: astropy>=5.3.2
Requires-Dist: h5py>=3.9.0
Requires-Dist: numpy>=1.15.0
